sav/info/__init__.py
sav-2020.2.dist-info/METADATA
sav-2020.2.dist-info/WHEEL
sav-2020.2.dist-info/top_level.txt
sav-2020.2.dist-info/RECORD
