Metadata-Version: 2.1
Name: sav
Version: 2020.2
Summary: Individual projects by Sander Voerman
Home-page: UNKNOWN
Author: Sander Voerman
Author-email: sander@savoerman.nl
License: UNKNOWN
Platform: UNKNOWN
Classifier: Topic :: Documentation
Requires-Python: >=3.7
